mongomantic/__init__.py
mongomantic/config.py
mongomantic/core/__init__.py
mongomantic/core/base_repository.py
mongomantic/core/database.py
mongomantic/core/errors.py
mongomantic/core/index.py
mongomantic/core/mongo_model.py
mongomantic/mongomantic.py
mongomantic/py.typed
mongomantic/utils/safe_repository.py
mongomantic-0.4.2.dist-info/entry_points.txt
mongomantic-0.4.2.dist-info/LICENSE
mongomantic-0.4.2.dist-info/WHEEL
mongomantic-0.4.2.dist-info/METADATA
mongomantic-0.4.2.dist-info/RECORD
