Metadata-Version: 2.1
Name: mongomantic
Version: 0.4.2
Summary: A MongoDB Python ORM, built on Pydantic and PyMongo.
Home-page: https://github.com/RamiAwar/mongomantic
License: MIT
Author: mongomantic
Author-email: rami@hyperchess.com
Requires-Python: >=3.7,<4.0
Classifier: Development Status :: 3 - Alpha
Classifier: Intended Audience :: Developers
Classifier: License :: OSI Approved :: MIT License
Classifier: Operating System :: OS Independent
Classifier: Programming Language :: Python :: 3
Classifier: Programming Language :: Python :: 3.7
Classifier: Programming Language :: Python :: 3.8
Classifier: Programming Language :: Python :: 3.9
Classifier: Topic :: Software Development :: Libraries :: Python Modules
Requires-Dist: bson (>=0.5.10,<0.6.0)
Requires-Dist: importlib_metadata (>=1.6,<5.0); python_version < "3.8"
Requires-Dist: pydantic (>=1.8.1,<2.0.0)
Requires-Dist: pymongo (>=3.11.3,<4.0.0)
Requires-Dist: requests (>=2.25.1,<3.0.0)
Requires-Dist: rich (>=9.8.2,<10.0.0)
Requires-Dist: wily (>=1.19.0,<2.0.0)
Project-URL: Repository, https://github.com/RamiAwar/mongomantic
